{
  "us_market": {
    "headline": "델 33% 급등이 주도…AI 인프라 수요 광풍",
    "summary": "29일 미국 증시에서 델(Dell)이 1분기 실적 호재로 33% 급등하며 지수 상승을 주도했다. AI 서버 수요 증가로 슈퍼마이크로컴퓨터, HP엔터프라이즈 등 관련 주들도 동반 상승했다. 로빈후드는 AI 거래 기술과 규제 진전에 힘입어 급등했으며, 리비안은 R2 SUV 출시 확정 소식에 반등했다.",
    "key_points": [
      "델 33% 상승으로 AI 인프라 수요 강세 재확인",
      "슈퍼마이크로·HP 등 서버·칩 주들 동반 상승",
      "로빈후드·리비안 등 개별 호재주 선별 강세"
    ]
  },
  "kr_market": {
    "headline": "트럼프 이란 협상 시장 변수…달러-원 1,504원대",
    "summary": "국제유가가 트럼프 종전협상 최종결정 앞두고 브렌트유 2% 하락했다. 달러-원 환율은 1,504.70원에서 마감해 상승폭이 축소된 상태다. 한투증권의 코인원 지분 인수에 대해 S&P가 재무역량 유지 가능성을 평가하며 긍정적 신호를 보냈다.",
    "key_points": [
      "국제유가 2% 하락…지정학적 리스크 완화 신호",
      "달러-원 1,504원대…트럼프 협상에 민감",
      "한투증권 코인원 인수, S&P 긍정 평가"
    ]
  },
  "news_curation": [
    {
      "title": "델 1분기 실적 호재로 33% 급등",
      "source": "Yahoo Finance Markets",
      "link": "https://finance.yahoo.com/m/4c4161ef-e87a-37db-bf3a-287eaa016f3c/dell%2C-rocket-lab%2C-palantir%2C.html?.tsrc=rss",
      "line1": "델이 AI 서버 수요 호실적으로 33% 상승",
      "line2": "PC·서버 메이커의 1분기 실적 강세가 촉발",
      "line3": "HP·슈퍼마이크로 등 IT 인프라주 동반 상승",
      "insight": "💡 AI 인프라 수요가 계속 확대되는 추세 속 관련 기업들의 실적 개선이 본격화되는 중. 공급 제약성 및 고마진 사업 성장성이 주목 대상."
    },
    {
      "title": "로빈후드 AI 거래·규제 진전으로 급등",
      "source": "Yahoo Finance Markets",
      "link": "https://www.fool.com/coverage/stock-market-today/2026/05/29/stock-market-today-may-29-robinhood-surges-despite-bitcoin-s-struggles/?.tsrc=rss",
      "line1": "로빈후드가 AI 거래 기술과 규제 진전으로 급등",
      "line2": "아나리스트 낙관론과 성장 전략 재평가가 배경",
      "line3": "암호화폐 약세에도 거래 플랫폼 수요 견고",
      "insight": "💡 핀테크 기업들의 AI 기술 도입과 규제 정상화가 수익성 개선 신호로 평가. 소매투자자 거래량 증가 추세와 연동."
    },
    {
      "title": "트럼프 이란 협상 앞두고 유가 2% 하락",
      "source": "연합뉴스 경제",
      "link": "https://www.yna.co.kr/view/AKR20260530005400072",
      "line1": "브렌트유가 트럼프 종전협상 앞두고 2% 하락",
      "line2": "미·이란 양해각서(MOU) 최종결정 준비 중",
      "line3": "종전 가능성 시장에 공급 확대 신호 전달",
      "insight": "💡 지정학적 리스크 해소 기대감이 유가 약세로 표현 중. 국내 에너지 수입가 인하 가능성으로 경기 긍정 신호."
    },
    {
      "title": "한투증권 코인원 인수, S&P 긍정 평가",
      "source": "연합뉴스 경제",
      "link": "https://www.yna.co.kr/view/AKR20260529167700008",
      "line1": "한투증권의 코인원 지분 20% 인수에 S&P 긍정",
      "line2": "인수 후에도 재무역량 유지 가능 평가",
      "line3": "가상자산 거래소 진출로 수익 다각화 추진",
      "insight": "💡 한투증권의 신사업 진출이 신용평가 기관에서 긍정 평가. 핀테크·암호화폐 부문 성장 베팅으로 해석 가능."
    },
    {
      "title": "달러-원 1,504원대 마감, 트럼프 협상 영향",
      "source": "연합뉴스 경제",
      "link": "https://www.yna.co.kr/view/AKR20260530003500002",
      "line1": "달러-원이 1,504.70원에 마감, 상승폭 축소",
      "line2": "미·이란 양해각서 최종결정 준비로 변동성 제한",
      "line3": "리스크 오프 심화 시 변동성 재확대 가능",
      "insight": "💡 미국의 대외 협상 결과에 따라 달러강세 추세가 일시 조정 중. 향후 협상 결과가 환율 방향성을 결정할 핵심 변수."
    }
  ],
  "investment_point": {
    "today_focus": "AI 인프라 수요의 본격 실적 반영 단계 진입이 주목 포인트다. 델의 33% 급등으로 AI 서버·칩 수요의 실체화가 확인되었으며, 국내 반도체주의 동반 상승 가능성이 높아지는 상황이다. 동시에 지정학적 리스크 완화(유가 하락)와 규제 정상화(핀테크) 신호들이 시장 심리를 지지하고 있다.",
    "risk_factor": "트럼프 종전협상의 결과 불확실성이 변수다. 협상 결과에 따라 유가와 환율이 급변할 수 있으며, 이는 에너지 수입 비중이 높은 국내 기업들과 수출 기업들에 직접 영향을 미친다. AST스페이스모바일 등 우주·위성 관련주의 급락은 장기 프로젝트 실행 리스크도 상기시킨다.",
    "opportunity": "AI 인프라 수요 확대 트렌드가 국내 반도체·IT 기업의 실적 개선으로 이어질 가능성이 높다. 또한 핀테크·암호화폐 규제 정상화 움직임은 국내 금융·기술 기업들의 신사업 확장 여지를 의미하며, 종전협상 진전은 에너지·수출 관련 기업들에 비용 부담 경감 기회를 제공할 수 있다."
  },
  "market_mood": "bullish"
}